main.py
apagea_jobs_core-0.0.1.dist-info/METADATA
apagea_jobs_core-0.0.1.dist-info/WHEEL
apagea_jobs_core-0.0.1.dist-info/top_level.txt
apagea_jobs_core-0.0.1.dist-info/RECORD
