Metadata-Version: 2.4
Name: apagea-jobs-core
Version: 0.0.1
Summary: Apagea Jobs Core
Requires-Python: >=3.13
